{"packages":{"insomnyawolf.AzureSamlSSO":["0.0.230916.182053-alpha"],"insomnyawolf.BasicIrcClient":["0.0.230916.182111-alpha"],"insomnyawolf.BooruApi":["0.0.230916.182055-alpha"],"insomnyawolf.CipherHelpers":["0.0.230916.182056-alpha"],"insomnyawolf.CliArgumentBuilder":["0.0.230916.182058-alpha"],"insomnyawolf.ConfigHelper":["1.0.0"],"insomnyawolf.CsvToObjects":["0.0.230916.182100-alpha"],"insomnyawolf.Extensions":["0.0.230916.182103-alpha"],"insomnyawolf.FastBitmap":["1.0.0"],"insomnyawolf.GithubHelper":["0.0.230916.182108-alpha"],"insomnyawolf.JwtHelper":["0.0.230916.182112-alpha"],"insomnyawolf.LayeredStorageNoAlloc":["0.0.230916.182113-alpha"],"insomnyawolf.LowLevelInputHooks":["0.0.230916.182115-alpha"],"insomnyawolf.MambaManager":["0.0.230916.182116-alpha"],"insomnyawolf.MathHelpers":["0.0.230916.182118-alpha"],"insomnyawolf.OauthClientBase":["0.0.230916.182120-alpha"],"insomnyawolf.OsuApiHelper":["0.0.230916.182121-alpha"],"insomnyawolf.RunicCypher":["0.0.230916.182125-alpha"],"insomnyawolf.SaucenaoSearch":["0.0.230916.182127-alpha"],"insomnyawolf.SimpleBruteForce":["0.0.230916.182129-alpha"],"insomnyawolf.SortingAlgorithms":["0.0.230916.182130-alpha"],"insomnyawolf.TypeConverterHelper":["0.0.230916.182134-alpha"],"insomnyawolf.UdpServer":["0.0.230916.182135-alpha"],"insomnyawolf.WinFormsApp1":["0.0.230916.182136-alpha"],"insomnyawolf.WorksheetToObjects":["0.0.230916.182138-alpha"],"insomnyawolf.YtDlpHelper":["0.0.230916.182139-alpha"]},"symbols":{"insomnyawolf.AzureSamlSSO":["0.0.230916.182053-alpha"],"insomnyawolf.BasicIrcClient":["0.0.230916.182111-alpha"],"insomnyawolf.BooruApi":["0.0.230916.182055-alpha"],"insomnyawolf.CipherHelpers":["0.0.230916.182056-alpha"],"insomnyawolf.CliArgumentBuilder":["0.0.230916.182058-alpha"],"insomnyawolf.ConfigHelper":["1.0.0"],"insomnyawolf.CsvToObjects":["0.0.230916.182100-alpha"],"insomnyawolf.Extensions":["0.0.230916.182103-alpha"],"insomnyawolf.FastBitmap":["1.0.0"],"insomnyawolf.GithubHelper":["0.0.230916.182108-alpha"],"insomnyawolf.JwtHelper":["0.0.230916.182112-alpha"],"insomnyawolf.LayeredStorageNoAlloc":["0.0.230916.182113-alpha"],"insomnyawolf.LowLevelInputHooks":["0.0.230916.182115-alpha"],"insomnyawolf.MambaManager":["0.0.230916.182116-alpha"],"insomnyawolf.MathHelpers":["0.0.230916.182118-alpha"],"insomnyawolf.OauthClientBase":["0.0.230916.182120-alpha"],"insomnyawolf.OsuApiHelper":["0.0.230916.182121-alpha"],"insomnyawolf.RunicCypher":["0.0.230916.182125-alpha"],"insomnyawolf.SaucenaoSearch":["0.0.230916.182127-alpha"],"insomnyawolf.SimpleBruteForce":["0.0.230916.182129-alpha"],"insomnyawolf.SortingAlgorithms":["0.0.230916.182130-alpha"],"insomnyawolf.TypeConverterHelper":["0.0.230916.182134-alpha"],"insomnyawolf.UdpServer":["0.0.230916.182135-alpha"],"insomnyawolf.WinFormsApp1":["0.0.230916.182136-alpha"],"insomnyawolf.WorksheetToObjects":["0.0.230916.182138-alpha"],"insomnyawolf.YtDlpHelper":["0.0.230916.182139-alpha"]}}